{
  "collectionName": "bulletin-boards_nboard",
  "info": {
    "name": "nboard",
    "description": "Notice Board"
  },
  "options": {
    "draftAndPublish": true,
    "increments": true,
    "timestamps": true,
    "comment": "notice board"
  },
  "attributes": {
    "type": {
      "type": "enumeration",
      "enum": ["article", "reply"]
    },
    "title": {
      "type": "string"
    },
    "content": {
      "type": "richtext"
    },
    "allowReply": {
      "type": "boolean",
      "default": false
    },
    "replies": {
      "collection": "bboard",
      "plugin": "bulletin-boards"
    },
    "user": {
      "model": "user",
      "plugin": "users-permissions"
    }
  }
}
